unicodekonverter/README.MD
unicodekonverter/__init__.py
unicodekonverter/requirements.txt
unicodekonverter/thirdparty.json
unicodekonverter-0.11.dist-info/LICENSE.rst
unicodekonverter-0.11.dist-info/METADATA
unicodekonverter-0.11.dist-info/WHEEL
unicodekonverter-0.11.dist-info/top_level.txt
unicodekonverter-0.11.dist-info/RECORD
