Metadata-Version: 2.1
Name: unicodekonverter
Version: 0.11
Summary: Converts Hexadecimal Unicode Codes with the prefix 'U+/u+' in text to Corresponding Characters
Home-page: https://github.com/hansalemaos/unicodekonverter
Author: Johannes Fischer
Author-email: aulasparticularesdealemaosp@gmail.com
License: MIT
Keywords: Convert,unicode,utf-8
Classifier: Development Status :: 4 - Beta
Classifier: Programming Language :: Python :: 3 :: Only
Classifier: Programming Language :: Python :: 3.10
Classifier: Topic :: Software Development :: Libraries :: Python Modules
Classifier: Topic :: Utilities
License-File: LICENSE.rst
Requires-Dist: baumregextrie
Requires-Dist: getfilenuitkapython
Requires-Dist: regex
